owners/__init__.py
owners/__main__.py
owners/_cli.py
owners/_colors.py
owners/_owners.py
owners/_rule.py
owners/_section.py
owners/commands/__init__.py
owners/commands/_base.py
owners/commands/_owned_by.py
owners/commands/_owners_of.py
owners/commands/_tree.py
owners/commands/_version.py
owners-0.1.2.dist-info/entry_points.txt
owners-0.1.2.dist-info/LICENSE
owners-0.1.2.dist-info/WHEEL
owners-0.1.2.dist-info/METADATA
owners-0.1.2.dist-info/RECORD
