Metadata-Version: 2.1
Name: owners
Version: 0.1.2
Summary: CLI tool to inspect CODEOWNERS file.
Keywords: codeowners,gitlab,owners,ownership
Author-email: Gram <git@orsinium.dev>
Requires-Python: >=3.8
Classifier: Development Status :: 5 - Production/Stable
Classifier: Intended Audience :: Developers
Classifier: License :: OSI Approved :: MIT License
Classifier: Programming Language :: Python
Classifier: Typing :: Typed
Requires-Dist: flake8 ; extra == "lint"
Requires-Dist: isort ; extra == "lint"
Requires-Dist: mypy ; extra == "lint"
Requires-Dist: unify ; extra == "lint"
Project-URL: Source, https://github.com/orsinium-labs/owners
Provides-Extra: lint
